grenouilleAPIClient/__init__.py
grenouilleAPIClient/client.py
grenouilleAPIClient-1.1.2.dist-info/METADATA
grenouilleAPIClient-1.1.2.dist-info/RECORD
grenouilleAPIClient-1.1.2.dist-info/WHEEL
grenouilleAPIClient-1.1.2.dist-info/top_level.txt
