Metadata-Version: 2.1
Name: grenouilleAPIClient
Version: 1.1.2
Summary: Python client designed to consume grenouilleAPI endpoints.
Home-page: https://github.com/FroggedTV/grenouilleAPIClientPython
Author: Vincent Philaeux Lamotte
Author-email: philaeux@the-cluster.org
License: UNKNOWN
Platform: UNKNOWN
Classifier: Programming Language :: Python :: 3
Classifier: License :: OSI Approved :: GNU General Public License v3 (GPLv3)
Classifier: Operating System :: OS Independent
